ela_reader/__init__.py
ela_reader/main.py
ela_reader/runinfo.py
ela_reader/formats/__init__.py
ela_reader/formats/log_reader.py
ela_reader/formats/naming.py
ela_reader/formats/vol_reader.py
ela_reader/formats/vtm_reader.py
ela_reader/tools/__init__.py
ela_reader/tools/free_surface.py
ela_reader-0.1.0.dist-info/licenses/LICENSE
ela_reader-0.1.0.dist-info/METADATA
ela_reader-0.1.0.dist-info/WHEEL
ela_reader-0.1.0.dist-info/top_level.txt
ela_reader-0.1.0.dist-info/RECORD
