Metadata-Version: 2.4
Name: ela-reader
Version: 0.1.0
Summary: Read and process the output files generated by FlexELA
Author: Declan B. Gaylo
License-Expression: MIT
Project-URL: Homepage, https://github.com/dgaylo/ela-reader
Project-URL: Bug Tracker, https://github.com/dgaylo/ela-reader/issues
Project-URL: Documentation, https://dgaylo.github.io/ela-reader
Classifier: Programming Language :: Python :: 3
Classifier: Operating System :: OS Independent
Requires-Python: >=3.10
License-File: LICENSE
Requires-Dist: numpy>=1
Requires-Dist: scipy>=1
Dynamic: license-file
